Metadata-Version: 2.1
Name: Check-If-Prime
Version: 1.1
Summary: returns true if the integer is prime else false
Home-page: https://github.com/panas18/check_prime
Author: Panas Tiwari
Author-email: panas.tiwary18@gmail.com
License: UNKNOWN
Platform: UNKNOWN
Classifier: Programming Language :: Python :: 3
Classifier: License :: OSI Approved :: MIT License
Classifier: Operating System :: OS Independent
License-File: LICENSE.txt
